filehashcache.py
filehashcache-0.1.0.dist-info/LICENSE
filehashcache-0.1.0.dist-info/METADATA
filehashcache-0.1.0.dist-info/WHEEL
filehashcache-0.1.0.dist-info/entry_points.txt
filehashcache-0.1.0.dist-info/top_level.txt
filehashcache-0.1.0.dist-info/RECORD
