Metadata-Version: 2.1
Name: filehashcache
Version: 0.1.0
Summary: A simple file-based caching system using hash-based file names
Author-email: Your Name <your.email@example.com>
Project-URL: Homepage, https://github.com/yourusername/filehashcache
Project-URL: Bug Tracker, https://github.com/yourusername/filehashcache/issues
Classifier: Programming Language :: Python :: 3
Classifier: License :: OSI Approved :: MIT License
Classifier: Operating System :: OS Independent
Requires-Python: >=3.7
License-File: LICENSE
